npa/__init__.py
npa-0.0.0.dist-info/LICENSE.txt
npa-0.0.0.dist-info/WHEEL
npa-0.0.0.dist-info/METADATA
npa-0.0.0.dist-info/RECORD
