Metadata-Version: 2.3
Name: npa
Version: 0.0.0
Summary: Normalized Pattern Analysis
Author-email: João Vitorino <jpmvo@outlook.com>
Requires-Python: >=3.9
Classifier: Intended Audience :: Developers
Classifier: Intended Audience :: Science/Research
Classifier: License :: OSI Approved
Classifier: License :: OSI Approved :: MIT License
Classifier: Operating System :: OS Independent
Classifier: Programming Language :: Python
Classifier: Programming Language :: Python :: 3
Classifier: Topic :: Adaptive Technologies
Classifier: Topic :: Scientific/Engineering
Classifier: Topic :: Scientific/Engineering :: Artificial Intelligence
Classifier: Topic :: Scientific/Engineering :: Information Analysis
Classifier: Topic :: Scientific/Engineering :: Mathematics
Classifier: Topic :: Scientific/Engineering :: Visualization
Classifier: Topic :: Security
Classifier: Topic :: Software Development
Classifier: Topic :: Software Development :: Libraries
Classifier: Topic :: Software Development :: Libraries :: Python Modules
Requires-Dist: numpy>=2.0.2,<3
Project-URL: Documentation, https://npa.readthedocs.io/en/latest/
Project-URL: Homepage, https://github.com/vitorinojoao/npa
